Jarvis/__init__.py
jarvis_stt_karthikeyan-0.1.0.dist-info/METADATA
jarvis_stt_karthikeyan-0.1.0.dist-info/WHEEL
jarvis_stt_karthikeyan-0.1.0.dist-info/top_level.txt
jarvis_stt_karthikeyan-0.1.0.dist-info/RECORD
