Metadata-Version: 2.4
Name: jarvis-stt-karthikeyan
Version: 0.1.0
Summary: This is a speech to text package created by Karthikeyan
Home-page: https://github.com/Karthikeyanmurugavel/Jarvis
Author: Karthikeyan
Author-email: karthikcristianosiuu@gmail.com
Classifier: Programming Language :: Python :: 3
Classifier: License :: OSI Approved :: MIT License
Classifier: Operating System :: OS Independent
Requires-Python: >=3.6
Requires-Dist: selenium
Requires-Dist: webdriver-manager
Dynamic: author
Dynamic: author-email
Dynamic: classifier
Dynamic: description
Dynamic: description-content-type
Dynamic: home-page
Dynamic: requires-dist
Dynamic: requires-python
Dynamic: summary
